gitlab_review_mcp/__init__.py
gitlab_review_mcp/config.py
gitlab_review_mcp/server.py
gitlab_review_mcp/services/__init__.py
gitlab_review_mcp/services/gitlab_service.py
gitlab_review_mcp/tools/__init__.py
gitlab_review_mcp/tools/gitlab_tools.py
gitlab_review_mcp/utils/__init__.py
gitlab_review_mcp/utils/logging.py
gitlab_review_mcp-0.2.0.dist-info/METADATA
gitlab_review_mcp-0.2.0.dist-info/WHEEL
gitlab_review_mcp-0.2.0.dist-info/entry_points.txt
gitlab_review_mcp-0.2.0.dist-info/licenses/LICENSE
gitlab_review_mcp-0.2.0.dist-info/RECORD
