Metadata-Version: 2.4
Name: gitlab-review-mcp
Version: 0.2.0
Summary: A Model Context Protocol (MCP) server implementation
Project-URL: Homepage, https://github.com/midodimori/gitlab-review-mcp
Project-URL: Repository, https://github.com/midodimori/gitlab-review-mcp
Project-URL: Issues, https://github.com/midodimori/gitlab-review-mcp/issues
Project-URL: Documentation, https://github.com/midodimori/gitlab-review-mcp#readme
Author-email: Minh DOAN <nhatminh.doan2702@gmail.com>
License: MIT License
License-File: LICENSE
Keywords: mcp,model-context-protocol,server
Classifier: Development Status :: 4 - Beta
Classifier: Intended Audience :: Developers
Classifier: License :: OSI Approved :: MIT License
Classifier: Operating System :: OS Independent
Classifier: Programming Language :: Python :: 3
Classifier: Programming Language :: Python :: 3.13
Classifier: Topic :: Software Development :: Libraries :: Python Modules
Requires-Python: >=3.13
Requires-Dist: fastmcp>=2.10.6
Requires-Dist: pydantic-settings>=2.8.5
Requires-Dist: pydantic>=2.11.7
Requires-Dist: python-dotenv>=1.1.1
Requires-Dist: python-gitlab>=4.13.0
Provides-Extra: dev
Requires-Dist: black>=25.1.0; extra == 'dev'
Requires-Dist: isort>=6.0.1; extra == 'dev'
Requires-Dist: mcp[cli]>=1.12.2; extra == 'dev'
Requires-Dist: mypy>=1.17.0; extra == 'dev'
Requires-Dist: pytest-asyncio>=1.1.0; extra == 'dev'
Requires-Dist: pytest-cov>=6.0.0; extra == 'dev'
Requires-Dist: pytest-mock>=3.14.1; extra == 'dev'
Requires-Dist: pytest>=8.4.1; extra == 'dev'
Requires-Dist: python-dotenv>=1.1.1; extra == 'dev'
Requires-Dist: ruff>=0.12.5; extra == 'dev'
